coord_convert/__init__.py
coord_convert/coordconvert.py
coord_convert/transform.py
coord_convert-0.2.1.dist-info/LICENSE
coord_convert-0.2.1.dist-info/METADATA
coord_convert-0.2.1.dist-info/WHEEL
coord_convert-0.2.1.dist-info/entry_points.txt
coord_convert-0.2.1.dist-info/top_level.txt
coord_convert-0.2.1.dist-info/RECORD
