Metadata-Version: 2.1
Name: coord-convert
Version: 0.2.1
Summary: china mars coordinate convertor.
Home-page: https://github.com/sshuair/coord-convert
Author: sshuair
Author-email: sshuair@gmail.com
License: UNKNOWN
Keywords: coordinate vector china
Platform: UNKNOWN
Classifier: Development Status :: 4 - Beta
Classifier: Intended Audience :: Developers
Classifier: Intended Audience :: Information Technology
Classifier: Intended Audience :: Science/Research
Classifier: License :: OSI Approved :: MIT License
Classifier: Programming Language :: C
Classifier: Programming Language :: Cython
Classifier: Programming Language :: Python :: 3.5
Classifier: Programming Language :: Python :: 3.6
Classifier: Programming Language :: Python :: 3
Classifier: Topic :: Multimedia :: Graphics :: Graphics Conversion
Classifier: Topic :: Scientific/Engineering :: GIS
Requires-Dist: click
Requires-Dist: tqdm
Requires-Dist: fiona
